ospa/__init__.py
ospa/ospa.py
ospa/ospa_exception.py
ospa-0.0.1.dist-info/LICENSE
ospa-0.0.1.dist-info/METADATA
ospa-0.0.1.dist-info/WHEEL
ospa-0.0.1.dist-info/top_level.txt
ospa-0.0.1.dist-info/RECORD
