Metadata-Version: 2.1
Name: ospa
Version: 0.0.1
Summary: OS extension
Home-page: https://github.com/kwentar/ospa
Author: Aleksei Alekseev
Author-email: alekseev.yeskela@gmail.com
License: UNKNOWN
Platform: UNKNOWN
Classifier: Programming Language :: Python :: 3
Classifier: License :: OSI Approved :: MIT License
Classifier: Operating System :: OS Independent
